oarepo_model_builder_drafts_files/__init__.py
oarepo_model_builder_drafts_files/builders/__init__.py
oarepo_model_builder_drafts_files/builders/files_service_config_disable_upload.py
oarepo_model_builder_drafts_files/builders/files_service_config_permission_prefix.py
oarepo_model_builder_drafts_files/builders/templates/__init__.py
oarepo_model_builder_drafts_files/builders/templates/draft_service_config_permission_prefix.py.jinja2
oarepo_model_builder_drafts_files/builders/templates/service_config_disable_upload.py.jinja2
oarepo_model_builder_drafts_files/builders/tests/__init__.py
oarepo_model_builder_drafts_files/builders/tests/conftest.py
oarepo_model_builder_drafts_files/builders/tests/test_resource.py
oarepo_model_builder_drafts_files/builders/tests/test_resource_input_data.py
oarepo_model_builder_drafts_files/builders/tests/templates/__init__.py
oarepo_model_builder_drafts_files/builders/tests/templates/conftest.py.jinja2
oarepo_model_builder_drafts_files/builders/tests/templates/test_files_resource.py.jinja2
oarepo_model_builder_drafts_files/builders/tests/templates/test_resource_input_data.py.jinja2
oarepo_model_builder_drafts_files/datatypes/__init__.py
oarepo_model_builder_drafts_files/datatypes/draft_file.py
oarepo_model_builder_drafts_files/datatypes/components/__init__.py
oarepo_model_builder_drafts_files/datatypes/components/draft_file_profile.py
oarepo_model_builder_drafts_files/datatypes/components/draft_files_tests.py
oarepo_model_builder_drafts_files/datatypes/components/drafts_files_record.py
oarepo_model_builder_drafts_files/datatypes/components/draft_file_model/__init__.py
oarepo_model_builder_drafts_files/datatypes/components/draft_file_model/blueprints.py
oarepo_model_builder_drafts_files/datatypes/components/draft_file_model/defaults.py
oarepo_model_builder_drafts_files/datatypes/components/draft_file_model/ext_resource.py
oarepo_model_builder_drafts_files/datatypes/components/draft_file_model/files_field.py
oarepo_model_builder_drafts_files-4.0.18.dist-info/METADATA
oarepo_model_builder_drafts_files-4.0.18.dist-info/WHEEL
oarepo_model_builder_drafts_files-4.0.18.dist-info/entry_points.txt
oarepo_model_builder_drafts_files-4.0.18.dist-info/top_level.txt
oarepo_model_builder_drafts_files-4.0.18.dist-info/RECORD
