Metadata-Version: 2.4
Name: oarepo-model-builder-drafts-files
Version: 4.0.18
Requires-Dist: oarepo-model-builder-tests>=4.0.0
Requires-Dist: oarepo-model-builder>=4.0.0
Requires-Dist: oarepo-model-builder-files>=4.0.0
Requires-Dist: oarepo-model-builder-drafts>=1.0.4
